cvldoc_parser-1.0.1.dist-info/METADATA
cvldoc_parser-1.0.1.dist-info/WHEEL
cvldoc_parser/__init__.py
cvldoc_parser/cvldoc_parser.pyd
cvldoc_parser-1.0.1.dist-info/RECORD
